BenbanfaXueC/README.md
BenbanfaXueC/__init__.py
BenbanfaXueC/__main__.py
BenbanfaXueC/file.epub
BenbanfaXueC/index.html
BenbanfaXueC/css/__init__.py
BenbanfaXueC/css/annotations.css
BenbanfaXueC/css/main.css
BenbanfaXueC/css/normalize.css
BenbanfaXueC/css/popup.css
BenbanfaXueC/font/__init__.py
BenbanfaXueC/font/fontello.eot
BenbanfaXueC/font/fontello.svg
BenbanfaXueC/font/fontello.ttf
BenbanfaXueC/font/fontello.woff
BenbanfaXueC/img/__init__.py
BenbanfaXueC/img/annotator-glyph-sprite.png
BenbanfaXueC/img/annotator-icon-sprite.png
BenbanfaXueC/img/apple-touch-icon.png
BenbanfaXueC/img/cancelfullscreen.png
BenbanfaXueC/img/close.png
BenbanfaXueC/img/fullscreen.png
BenbanfaXueC/img/loader.gif
BenbanfaXueC/img/menu-icon.png
BenbanfaXueC/img/save.png
BenbanfaXueC/img/saved.png
BenbanfaXueC/img/settings-s.png
BenbanfaXueC/img/settings.png
BenbanfaXueC/img/star.png
BenbanfaXueC/js/__init__.py
BenbanfaXueC/js/epub.js
BenbanfaXueC/js/epub.min.js
BenbanfaXueC/js/epub.min.map
BenbanfaXueC/js/hooks.min.js
BenbanfaXueC/js/hooks.min.map
BenbanfaXueC/js/reader.js
BenbanfaXueC/js/reader.js.map
BenbanfaXueC/js/reader.min.js
BenbanfaXueC/js/reader.min.map
BenbanfaXueC/js/hooks/__init__.py
BenbanfaXueC/js/hooks/extensions/__init__.py
BenbanfaXueC/js/hooks/extensions/highlight.js
BenbanfaXueC/js/libs/__init__.py
BenbanfaXueC/js/libs/jquery.min.js
BenbanfaXueC/js/libs/localforage.min.js
BenbanfaXueC/js/libs/screenfull.js
BenbanfaXueC/js/libs/screenfull.min.js
BenbanfaXueC/js/libs/zip.min.js
BenbanfaXueC/js/plugins/__init__.py
BenbanfaXueC/js/plugins/hypothesis.js
BenbanfaXueC/js/plugins/search.js
benbanfa_xue_c-2024.3.1.0.dist-info/METADATA
benbanfa_xue_c-2024.3.1.0.dist-info/WHEEL
benbanfa_xue_c-2024.3.1.0.dist-info/entry_points.txt
benbanfa_xue_c-2024.3.1.0.dist-info/top_level.txt
benbanfa_xue_c-2024.3.1.0.dist-info/RECORD
